pixyzrl/__init__.py
pixyzrl/utils.py
pixyzrl/environments/__init__.py
pixyzrl/environments/env.py
pixyzrl/logger/__init__.py
pixyzrl/logger/logger.py
pixyzrl/losses/__init__.py
pixyzrl/losses/losses.py
pixyzrl/memory/__init__.py
pixyzrl/memory/memory.py
pixyzrl/models/__init__.py
pixyzrl/models/base_model.py
pixyzrl/models/off_policy/__init__.py
pixyzrl/models/off_policy/dqn.py
pixyzrl/models/on_policy/__init__.py
pixyzrl/models/on_policy/a2c.py
pixyzrl/models/on_policy/ppo.py
pixyzrl/pomdp/rssm.py
pixyzrl/trainer/__init__.py
pixyzrl/trainer/base_trainer.py
pixyzrl/trainer/off_policy_trainer/__init__.py
pixyzrl/trainer/off_policy_trainer/trainer.py
pixyzrl/trainer/on_policy_trainer/__init__.py
pixyzrl/trainer/on_policy_trainer/trainer.py
pixyzrl-0.3.0.dist-info/licenses/LICENSE
pixyzrl-0.3.0.dist-info/METADATA
pixyzrl-0.3.0.dist-info/WHEEL
pixyzrl-0.3.0.dist-info/top_level.txt
pixyzrl-0.3.0.dist-info/RECORD
