Metadata-Version: 2.4
Name: pixyzrl
Version: 0.3.0
Summary: Reinforcement Learning with Pixyz (PixyzRL)
Author-email: Masaki Ito <ito.masaki@em.ci.ritsumei.ac.jp>
Maintainer-email: Masaki Ito <ito.masaki@em.ci.ritsumei.ac.jp>
License: MIT License
Project-URL: Repository, https://github.com/ItoMasaki/PixyzRL
Keywords: pixyzrl,pixyz
Classifier: Development Status :: 4 - Beta
Classifier: Programming Language :: Python :: 3.10
Classifier: Operating System :: OS Independent
Classifier: License :: OSI Approved :: MIT License
Classifier: Topic :: Scientific/Engineering :: Artificial Intelligence
Requires-Python: >=3.10
License-File: LICENSE
Requires-Dist: swig
Requires-Dist: torch>=2.1.1
Requires-Dist: torchaudio>=2.1.1
Requires-Dist: torchvision>=0.16.1
Requires-Dist: pixyz
Requires-Dist: gymnasium[box2d]
Requires-Dist: torchrl
Requires-Dist: tensorboardX>=2.6.0
Requires-Dist: matplotlib
Requires-Dist: pybullet
Requires-Dist: ffmpeg-python
Provides-Extra: dev
Requires-Dist: black; extra == "dev"
Requires-Dist: flake8; extra == "dev"
Requires-Dist: mypy; extra == "dev"
Requires-Dist: isort; extra == "dev"
Requires-Dist: pre-commit; extra == "dev"
Requires-Dist: pytest; extra == "dev"
Requires-Dist: pytest-cov; extra == "dev"
Provides-Extra: gitlab-ci
Requires-Dist: coverage>=7.3.2; extra == "gitlab-ci"
Requires-Dist: pytest>=7.4.3; extra == "gitlab-ci"
Dynamic: license-file
